[
    {
        "model": "socialaccount.socialapp",
        "pk": 1,
        "fields": {
            "provider": "github",
            "name": "Github",
            "client_id": "0492d42045b4fc676533",
            "secret": "askwherethisislocated",
            "key": "",
            "sites": [
                1
            ]
        }
    },
    {
        "model": "socialaccount.socialaccount",
        "pk": 1,
        "fields": {
            "user": 8,
            "provider": "github",
            "uid": "218592",
            "last_login": "2022-01-14T19:14:55.900Z",
            "date_joined": "2021-12-05T03:30:23.548Z",
            "extra_data": "{\"login\": \"stevebrownlee\", \"id\": 218592, \"node_id\": \"MDQ6VXNlcjIxODU5Mg==\", \"avatar_url\": \"https://avatars.githubusercontent.com/u/218592?v=4\", \"gravatar_id\": \"\", \"url\": \"https://api.github.com/users/stevebrownlee\", \"html_url\": \"https://github.com/stevebrownlee\", \"followers_url\": \"https://api.github.com/users/stevebrownlee/followers\", \"following_url\": \"https://api.github.com/users/stevebrownlee/following{/other_user}\", \"gists_url\": \"https://api.github.com/users/stevebrownlee/gists{/gist_id}\", \"starred_url\": \"https://api.github.com/users/stevebrownlee/starred{/owner}{/repo}\", \"subscriptions_url\": \"https://api.github.com/users/stevebrownlee/subscriptions\", \"organizations_url\": \"https://api.github.com/users/stevebrownlee/orgs\", \"repos_url\": \"https://api.github.com/users/stevebrownlee/repos\", \"events_url\": \"https://api.github.com/users/stevebrownlee/events{/privacy}\", \"received_events_url\": \"https://api.github.com/users/stevebrownlee/received_events\", \"type\": \"User\", \"site_admin\": false, \"name\": \"Steve Brownlee\", \"company\": \"@nashville-software-school \", \"blog\": \"http://www.stevebrownlee.com\", \"location\": \"Nashville, TN\", \"email\": null, \"hireable\": true, \"bio\": \"Head Coach @nashville-software-school\", \"twitter_username\": null, \"public_repos\": 106, \"public_gists\": 17, \"followers\": 321, \"following\": 4, \"created_at\": \"2010-03-08T20:39:55Z\", \"updated_at\": \"2021-09-30T15:13:12Z\"}"
        }
    },
    {
        "model": "socialaccount.socialaccount",
        "pk": 2,
        "fields": {
            "user": 9,
            "provider": "github",
            "uid": "57766594",
            "last_login": "2021-12-31T05:08:01.429Z",
            "date_joined": "2021-12-05T15:31:01.140Z",
            "extra_data": "{\"login\": \"mbrownlee\", \"id\": 57766594, \"node_id\": \"MDQ6VXNlcjU3NzY2NTk0\", \"avatar_url\": \"https://avatars.githubusercontent.com/u/57766594?v=4\", \"gravatar_id\": \"\", \"url\": \"https://api.github.com/users/mbrownlee\", \"html_url\": \"https://github.com/mbrownlee\", \"followers_url\": \"https://api.github.com/users/mbrownlee/followers\", \"following_url\": \"https://api.github.com/users/mbrownlee/following{/other_user}\", \"gists_url\": \"https://api.github.com/users/mbrownlee/gists{/gist_id}\", \"starred_url\": \"https://api.github.com/users/mbrownlee/starred{/owner}{/repo}\", \"subscriptions_url\": \"https://api.github.com/users/mbrownlee/subscriptions\", \"organizations_url\": \"https://api.github.com/users/mbrownlee/orgs\", \"repos_url\": \"https://api.github.com/users/mbrownlee/repos\", \"events_url\": \"https://api.github.com/users/mbrownlee/events{/privacy}\", \"received_events_url\": \"https://api.github.com/users/mbrownlee/received_events\", \"type\": \"User\", \"site_admin\": false, \"name\": \"Michelle\", \"company\": null, \"blog\": \"\", \"location\": null, \"email\": null, \"hireable\": null, \"bio\": null, \"twitter_username\": null, \"public_repos\": 67, \"public_gists\": 0, \"followers\": 7, \"following\": 0, \"created_at\": \"2019-11-14T16:42:01Z\", \"updated_at\": \"2021-12-30T05:53:26Z\"}"
        }
    },
    {
        "model": "socialaccount.socialaccount",
        "pk": 3,
        "fields": {
            "user": 10,
            "provider": "github",
            "uid": "3247835",
            "last_login": "2021-12-11T19:04:03.093Z",
            "date_joined": "2021-12-11T16:15:10.045Z",
            "extra_data": "{\"login\": \"JoeShep\", \"id\": 3247835, \"node_id\": \"MDQ6VXNlcjMyNDc4MzU=\", \"avatar_url\": \"https://avatars.githubusercontent.com/u/3247835?v=4\", \"gravatar_id\": \"\", \"url\": \"https://api.github.com/users/JoeShep\", \"html_url\": \"https://github.com/JoeShep\", \"followers_url\": \"https://api.github.com/users/JoeShep/followers\", \"following_url\": \"https://api.github.com/users/JoeShep/following{/other_user}\", \"gists_url\": \"https://api.github.com/users/JoeShep/gists{/gist_id}\", \"starred_url\": \"https://api.github.com/users/JoeShep/starred{/owner}{/repo}\", \"subscriptions_url\": \"https://api.github.com/users/JoeShep/subscriptions\", \"organizations_url\": \"https://api.github.com/users/JoeShep/orgs\", \"repos_url\": \"https://api.github.com/users/JoeShep/repos\", \"events_url\": \"https://api.github.com/users/JoeShep/events{/privacy}\", \"received_events_url\": \"https://api.github.com/users/JoeShep/received_events\", \"type\": \"User\", \"site_admin\": false, \"name\": \"Joe Shepherd\", \"company\": \"Nashville Software School\", \"blog\": \"\", \"location\": \"Nashville\", \"email\": null, \"hireable\": true, \"bio\": null, \"twitter_username\": null, \"public_repos\": 145, \"public_gists\": 26, \"followers\": 161, \"following\": 3, \"created_at\": \"2013-01-11T21:06:16Z\", \"updated_at\": \"2021-11-11T19:26:01Z\"}"
        }
    },
    {
        "model": "socialaccount.socialaccount",
        "pk": 4,
        "fields": {
            "user": 11,
            "provider": "github",
            "uid": "74211798",
            "last_login": "2021-12-11T19:28:29.085Z",
            "date_joined": "2021-12-11T16:15:57.268Z",
            "extra_data": "{\"login\": \"christinaashworth\", \"id\": 74211798, \"node_id\": \"MDQ6VXNlcjc0MjExNzk4\", \"avatar_url\": \"https://avatars.githubusercontent.com/u/74211798?v=4\", \"gravatar_id\": \"\", \"url\": \"https://api.github.com/users/christinaashworth\", \"html_url\": \"https://github.com/christinaashworth\", \"followers_url\": \"https://api.github.com/users/christinaashworth/followers\", \"following_url\": \"https://api.github.com/users/christinaashworth/following{/other_user}\", \"gists_url\": \"https://api.github.com/users/christinaashworth/gists{/gist_id}\", \"starred_url\": \"https://api.github.com/users/christinaashworth/starred{/owner}{/repo}\", \"subscriptions_url\": \"https://api.github.com/users/christinaashworth/subscriptions\", \"organizations_url\": \"https://api.github.com/users/christinaashworth/orgs\", \"repos_url\": \"https://api.github.com/users/christinaashworth/repos\", \"events_url\": \"https://api.github.com/users/christinaashworth/events{/privacy}\", \"received_events_url\": \"https://api.github.com/users/christinaashworth/received_events\", \"type\": \"User\", \"site_admin\": false, \"name\": null, \"company\": null, \"blog\": \"\", \"location\": null, \"email\": null, \"hireable\": null, \"bio\": null, \"twitter_username\": null, \"public_repos\": 27, \"public_gists\": 0, \"followers\": 7, \"following\": 1, \"created_at\": \"2020-11-09T20:27:35Z\", \"updated_at\": \"2021-11-17T21:18:21Z\"}"
        }
    },
    {
        "model": "socialaccount.socialaccount",
        "pk": 5,
        "fields": {
            "user": 12,
            "provider": "github",
            "uid": "57641436",
            "last_login": "2021-12-11T19:28:35.177Z",
            "date_joined": "2021-12-11T16:16:36.051Z",
            "extra_data": "{\"login\": \"ajawashington\", \"id\": 57641436, \"node_id\": \"MDQ6VXNlcjU3NjQxNDM2\", \"avatar_url\": \"https://avatars.githubusercontent.com/u/57641436?v=4\", \"gravatar_id\": \"\", \"url\": \"https://api.github.com/users/ajawashington\", \"html_url\": \"https://github.com/ajawashington\", \"followers_url\": \"https://api.github.com/users/ajawashington/followers\", \"following_url\": \"https://api.github.com/users/ajawashington/following{/other_user}\", \"gists_url\": \"https://api.github.com/users/ajawashington/gists{/gist_id}\", \"starred_url\": \"https://api.github.com/users/ajawashington/starred{/owner}{/repo}\", \"subscriptions_url\": \"https://api.github.com/users/ajawashington/subscriptions\", \"organizations_url\": \"https://api.github.com/users/ajawashington/orgs\", \"repos_url\": \"https://api.github.com/users/ajawashington/repos\", \"events_url\": \"https://api.github.com/users/ajawashington/events{/privacy}\", \"received_events_url\": \"https://api.github.com/users/ajawashington/received_events\", \"type\": \"User\", \"site_admin\": false, \"name\": \"Aja\", \"company\": null, \"blog\": \"\", \"location\": \"Nashville, TN\", \"email\": null, \"hireable\": null, \"bio\": null, \"twitter_username\": \"_ayejah\", \"public_repos\": 53, \"public_gists\": 1, \"followers\": 31, \"following\": 10, \"created_at\": \"2019-11-11T20:14:02Z\", \"updated_at\": \"2021-11-20T15:07:13Z\"}"
        }
    },
    {
        "model": "socialaccount.socialaccount",
        "pk": 6,
        "fields": {
            "user": 13,
            "provider": "github",
            "uid": "65423687",
            "last_login": "2022-01-14T22:21:52.003Z",
            "date_joined": "2022-01-02T01:00:23.633Z",
            "extra_data": "{\"login\": \"tylerghilliard94\", \"id\": 65423687, \"node_id\": \"MDQ6VXNlcjY1NDIzNjg3\", \"avatar_url\": \"https://avatars.githubusercontent.com/u/65423687?v=4\", \"gravatar_id\": \"\", \"url\": \"https://api.github.com/users/tylerghilliard94\", \"html_url\": \"https://github.com/tylerghilliard94\", \"followers_url\": \"https://api.github.com/users/tylerghilliard94/followers\", \"following_url\": \"https://api.github.com/users/tylerghilliard94/following{/other_user}\", \"gists_url\": \"https://api.github.com/users/tylerghilliard94/gists{/gist_id}\", \"starred_url\": \"https://api.github.com/users/tylerghilliard94/starred{/owner}{/repo}\", \"subscriptions_url\": \"https://api.github.com/users/tylerghilliard94/subscriptions\", \"organizations_url\": \"https://api.github.com/users/tylerghilliard94/orgs\", \"repos_url\": \"https://api.github.com/users/tylerghilliard94/repos\", \"events_url\": \"https://api.github.com/users/tylerghilliard94/events{/privacy}\", \"received_events_url\": \"https://api.github.com/users/tylerghilliard94/received_events\", \"type\": \"User\", \"site_admin\": false, \"name\": \"Tyler Hilliard\", \"company\": null, \"blog\": \"\", \"location\": null, \"email\": null, \"hireable\": null, \"bio\": null, \"twitter_username\": null, \"public_repos\": 53, \"public_gists\": 0, \"followers\": 13, \"following\": 0, \"created_at\": \"2020-05-15T20:49:45Z\", \"updated_at\": \"2022-01-06T16:18:41Z\"}"
        }
    },
    {
        "model": "socialaccount.socialaccount",
        "pk": 7,
        "fields": {
            "user": 14,
            "provider": "github",
            "uid": "96741689",
            "last_login": "2022-01-06T15:12:01.128Z",
            "date_joined": "2022-01-06T15:02:44.059Z",
            "extra_data": "{\"login\": \"Callmesince\", \"id\": 96741689, \"node_id\": \"U_kgDOBcQpOQ\", \"avatar_url\": \"https://avatars.githubusercontent.com/u/96741689?v=4\", \"gravatar_id\": \"\", \"url\": \"https://api.github.com/users/Callmesince\", \"html_url\": \"https://github.com/Callmesince\", \"followers_url\": \"https://api.github.com/users/Callmesince/followers\", \"following_url\": \"https://api.github.com/users/Callmesince/following{/other_user}\", \"gists_url\": \"https://api.github.com/users/Callmesince/gists{/gist_id}\", \"starred_url\": \"https://api.github.com/users/Callmesince/starred{/owner}{/repo}\", \"subscriptions_url\": \"https://api.github.com/users/Callmesince/subscriptions\", \"organizations_url\": \"https://api.github.com/users/Callmesince/orgs\", \"repos_url\": \"https://api.github.com/users/Callmesince/repos\", \"events_url\": \"https://api.github.com/users/Callmesince/events{/privacy}\", \"received_events_url\": \"https://api.github.com/users/Callmesince/received_events\", \"type\": \"User\", \"site_admin\": false, \"name\": \"christian haggerty\", \"company\": null, \"blog\": \"\", \"location\": null, \"email\": null, \"hireable\": null, \"bio\": null, \"twitter_username\": null, \"public_repos\": 0, \"public_gists\": 0, \"followers\": 0, \"following\": 0, \"created_at\": \"2021-12-27T17:07:27Z\", \"updated_at\": \"2022-01-03T19:11:05Z\"}"
        }
    },
    {
        "model": "socialaccount.socialaccount",
        "pk": 8,
        "fields": {
            "user": 15,
            "provider": "github",
            "uid": "85896879",
            "last_login": "2022-01-06T15:12:15.997Z",
            "date_joined": "2022-01-06T15:02:57.718Z",
            "extra_data": "{\"login\": \"TomHawk123\", \"id\": 85896879, \"node_id\": \"MDQ6VXNlcjg1ODk2ODc5\", \"avatar_url\": \"https://avatars.githubusercontent.com/u/85896879?v=4\", \"gravatar_id\": \"\", \"url\": \"https://api.github.com/users/TomHawk123\", \"html_url\": \"https://github.com/TomHawk123\", \"followers_url\": \"https://api.github.com/users/TomHawk123/followers\", \"following_url\": \"https://api.github.com/users/TomHawk123/following{/other_user}\", \"gists_url\": \"https://api.github.com/users/TomHawk123/gists{/gist_id}\", \"starred_url\": \"https://api.github.com/users/TomHawk123/starred{/owner}{/repo}\", \"subscriptions_url\": \"https://api.github.com/users/TomHawk123/subscriptions\", \"organizations_url\": \"https://api.github.com/users/TomHawk123/orgs\", \"repos_url\": \"https://api.github.com/users/TomHawk123/repos\", \"events_url\": \"https://api.github.com/users/TomHawk123/events{/privacy}\", \"received_events_url\": \"https://api.github.com/users/TomHawk123/received_events\", \"type\": \"User\", \"site_admin\": false, \"name\": \"Matthew McMorries\", \"company\": null, \"blog\": \"\", \"location\": null, \"email\": null, \"hireable\": null, \"bio\": null, \"twitter_username\": null, \"public_repos\": 0, \"public_gists\": 0, \"followers\": 0, \"following\": 1, \"created_at\": \"2021-06-14T17:14:09Z\", \"updated_at\": \"2022-01-06T15:09:36Z\"}"
        }
    },
    {
        "model": "socialaccount.socialaccount",
        "pk": 9,
        "fields": {
            "user": 16,
            "provider": "github",
            "uid": "96507192",
            "last_login": "2022-01-13T22:12:16.851Z",
            "date_joined": "2022-01-06T15:05:48.799Z",
            "extra_data": "{\"login\": \"HoTcHiCkEn615\", \"id\": 96507192, \"node_id\": \"U_kgDOBcCVOA\", \"avatar_url\": \"https://avatars.githubusercontent.com/u/96507192?v=4\", \"gravatar_id\": \"\", \"url\": \"https://api.github.com/users/HoTcHiCkEn615\", \"html_url\": \"https://github.com/HoTcHiCkEn615\", \"followers_url\": \"https://api.github.com/users/HoTcHiCkEn615/followers\", \"following_url\": \"https://api.github.com/users/HoTcHiCkEn615/following{/other_user}\", \"gists_url\": \"https://api.github.com/users/HoTcHiCkEn615/gists{/gist_id}\", \"starred_url\": \"https://api.github.com/users/HoTcHiCkEn615/starred{/owner}{/repo}\", \"subscriptions_url\": \"https://api.github.com/users/HoTcHiCkEn615/subscriptions\", \"organizations_url\": \"https://api.github.com/users/HoTcHiCkEn615/orgs\", \"repos_url\": \"https://api.github.com/users/HoTcHiCkEn615/repos\", \"events_url\": \"https://api.github.com/users/HoTcHiCkEn615/events{/privacy}\", \"received_events_url\": \"https://api.github.com/users/HoTcHiCkEn615/received_events\", \"type\": \"User\", \"site_admin\": false, \"name\": \"Riley Phillips\", \"company\": null, \"blog\": \"\", \"location\": null, \"email\": null, \"hireable\": null, \"bio\": null, \"twitter_username\": null, \"public_repos\": 4, \"public_gists\": 0, \"followers\": 0, \"following\": 0, \"created_at\": \"2021-12-22T02:00:56Z\", \"updated_at\": \"2022-01-07T19:05:52Z\"}"
        }
    },
    {
        "model": "socialaccount.socialaccount",
        "pk": 10,
        "fields": {
            "user": 17,
            "provider": "github",
            "uid": "91995696",
            "last_login": "2022-01-06T15:12:02.655Z",
            "date_joined": "2022-01-06T15:05:50.056Z",
            "extra_data": "{\"login\": \"HankHaus\", \"id\": 91995696, \"node_id\": \"U_kgDOBXu-MA\", \"avatar_url\": \"https://avatars.githubusercontent.com/u/91995696?v=4\", \"gravatar_id\": \"\", \"url\": \"https://api.github.com/users/HankHaus\", \"html_url\": \"https://github.com/HankHaus\", \"followers_url\": \"https://api.github.com/users/HankHaus/followers\", \"following_url\": \"https://api.github.com/users/HankHaus/following{/other_user}\", \"gists_url\": \"https://api.github.com/users/HankHaus/gists{/gist_id}\", \"starred_url\": \"https://api.github.com/users/HankHaus/starred{/owner}{/repo}\", \"subscriptions_url\": \"https://api.github.com/users/HankHaus/subscriptions\", \"organizations_url\": \"https://api.github.com/users/HankHaus/orgs\", \"repos_url\": \"https://api.github.com/users/HankHaus/repos\", \"events_url\": \"https://api.github.com/users/HankHaus/events{/privacy}\", \"received_events_url\": \"https://api.github.com/users/HankHaus/received_events\", \"type\": \"User\", \"site_admin\": false, \"name\": \"Henry House\", \"company\": null, \"blog\": \"\", \"location\": null, \"email\": null, \"hireable\": null, \"bio\": null, \"twitter_username\": null, \"public_repos\": 0, \"public_gists\": 0, \"followers\": 0, \"following\": 0, \"created_at\": \"2021-10-05T22:29:21Z\", \"updated_at\": \"2022-01-06T15:09:10Z\"}"
        }
    },
    {
        "model": "socialaccount.socialaccount",
        "pk": 11,
        "fields": {
            "user": 18,
            "provider": "github",
            "uid": "97009690",
            "last_login": "2022-01-06T15:12:17.724Z",
            "date_joined": "2022-01-06T15:05:50.552Z",
            "extra_data": "{\"login\": \"Semiosphere\", \"id\": 97009690, \"node_id\": \"U_kgDOBchAGg\", \"avatar_url\": \"https://avatars.githubusercontent.com/u/97009690?v=4\", \"gravatar_id\": \"\", \"url\": \"https://api.github.com/users/Semiosphere\", \"html_url\": \"https://github.com/Semiosphere\", \"followers_url\": \"https://api.github.com/users/Semiosphere/followers\", \"following_url\": \"https://api.github.com/users/Semiosphere/following{/other_user}\", \"gists_url\": \"https://api.github.com/users/Semiosphere/gists{/gist_id}\", \"starred_url\": \"https://api.github.com/users/Semiosphere/starred{/owner}{/repo}\", \"subscriptions_url\": \"https://api.github.com/users/Semiosphere/subscriptions\", \"organizations_url\": \"https://api.github.com/users/Semiosphere/orgs\", \"repos_url\": \"https://api.github.com/users/Semiosphere/repos\", \"events_url\": \"https://api.github.com/users/Semiosphere/events{/privacy}\", \"received_events_url\": \"https://api.github.com/users/Semiosphere/received_events\", \"type\": \"User\", \"site_admin\": false, \"name\": \"Zach Dugger\", \"company\": null, \"blog\": \"\", \"location\": null, \"email\": null, \"hireable\": null, \"bio\": \"@ZTD_Illustrated\", \"twitter_username\": null, \"public_repos\": 0, \"public_gists\": 0, \"followers\": 0, \"following\": 0, \"created_at\": \"2022-01-03T04:11:17Z\", \"updated_at\": \"2022-01-06T15:08:37Z\"}"
        }
    },
    {
        "model": "socialaccount.socialaccount",
        "pk": 12,
        "fields": {
            "user": 19,
            "provider": "github",
            "uid": "93087995",
            "last_login": "2022-01-06T15:12:01.801Z",
            "date_joined": "2022-01-06T15:05:51.151Z",
            "extra_data": "{\"login\": \"DevDevvy\", \"id\": 93087995, \"node_id\": \"U_kgDOBYxo-w\", \"avatar_url\": \"https://avatars.githubusercontent.com/u/93087995?v=4\", \"gravatar_id\": \"\", \"url\": \"https://api.github.com/users/DevDevvy\", \"html_url\": \"https://github.com/DevDevvy\", \"followers_url\": \"https://api.github.com/users/DevDevvy/followers\", \"following_url\": \"https://api.github.com/users/DevDevvy/following{/other_user}\", \"gists_url\": \"https://api.github.com/users/DevDevvy/gists{/gist_id}\", \"starred_url\": \"https://api.github.com/users/DevDevvy/starred{/owner}{/repo}\", \"subscriptions_url\": \"https://api.github.com/users/DevDevvy/subscriptions\", \"organizations_url\": \"https://api.github.com/users/DevDevvy/orgs\", \"repos_url\": \"https://api.github.com/users/DevDevvy/repos\", \"events_url\": \"https://api.github.com/users/DevDevvy/events{/privacy}\", \"received_events_url\": \"https://api.github.com/users/DevDevvy/received_events\", \"type\": \"User\", \"site_admin\": false, \"name\": \"Randall Thomas\", \"company\": null, \"blog\": \"\", \"location\": null, \"email\": null, \"hireable\": null, \"bio\": \"I am a multimedia creator in multiple industries. Writer, singer, music producer, podcaster, and most recently web developer. \", \"twitter_username\": null, \"public_repos\": 0, \"public_gists\": 0, \"followers\": 0, \"following\": 0, \"created_at\": \"2021-10-24T15:04:17Z\", \"updated_at\": \"2022-01-06T15:09:39Z\"}"
        }
    },
    {
        "model": "socialaccount.socialaccount",
        "pk": 13,
        "fields": {
            "user": 20,
            "provider": "github",
            "uid": "90797657",
            "last_login": "2022-01-06T15:12:10.904Z",
            "date_joined": "2022-01-06T15:05:52.899Z",
            "extra_data": "{\"login\": \"ChelseaHarrisW\", \"id\": 90797657, \"node_id\": \"MDQ6VXNlcjkwNzk3NjU3\", \"avatar_url\": \"https://avatars.githubusercontent.com/u/90797657?v=4\", \"gravatar_id\": \"\", \"url\": \"https://api.github.com/users/ChelseaHarrisW\", \"html_url\": \"https://github.com/ChelseaHarrisW\", \"followers_url\": \"https://api.github.com/users/ChelseaHarrisW/followers\", \"following_url\": \"https://api.github.com/users/ChelseaHarrisW/following{/other_user}\", \"gists_url\": \"https://api.github.com/users/ChelseaHarrisW/gists{/gist_id}\", \"starred_url\": \"https://api.github.com/users/ChelseaHarrisW/starred{/owner}{/repo}\", \"subscriptions_url\": \"https://api.github.com/users/ChelseaHarrisW/subscriptions\", \"organizations_url\": \"https://api.github.com/users/ChelseaHarrisW/orgs\", \"repos_url\": \"https://api.github.com/users/ChelseaHarrisW/repos\", \"events_url\": \"https://api.github.com/users/ChelseaHarrisW/events{/privacy}\", \"received_events_url\": \"https://api.github.com/users/ChelseaHarrisW/received_events\", \"type\": \"User\", \"site_admin\": false, \"name\": \"Chelsea Harris\", \"company\": null, \"blog\": \"\", \"location\": null, \"email\": null, \"hireable\": null, \"bio\": null, \"twitter_username\": null, \"public_repos\": 12, \"public_gists\": 0, \"followers\": 0, \"following\": 0, \"created_at\": \"2021-09-15T19:26:00Z\", \"updated_at\": \"2022-01-06T15:08:12Z\"}"
        }
    },
    {
        "model": "socialaccount.socialaccount",
        "pk": 14,
        "fields": {
            "user": 21,
            "provider": "github",
            "uid": "96712524",
            "last_login": "2022-01-06T16:57:45.574Z",
            "date_joined": "2022-01-06T15:05:53.486Z",
            "extra_data": "{\"login\": \"noahtaggart\", \"id\": 96712524, \"node_id\": \"U_kgDOBcO3TA\", \"avatar_url\": \"https://avatars.githubusercontent.com/u/96712524?v=4\", \"gravatar_id\": \"\", \"url\": \"https://api.github.com/users/noahtaggart\", \"html_url\": \"https://github.com/noahtaggart\", \"followers_url\": \"https://api.github.com/users/noahtaggart/followers\", \"following_url\": \"https://api.github.com/users/noahtaggart/following{/other_user}\", \"gists_url\": \"https://api.github.com/users/noahtaggart/gists{/gist_id}\", \"starred_url\": \"https://api.github.com/users/noahtaggart/starred{/owner}{/repo}\", \"subscriptions_url\": \"https://api.github.com/users/noahtaggart/subscriptions\", \"organizations_url\": \"https://api.github.com/users/noahtaggart/orgs\", \"repos_url\": \"https://api.github.com/users/noahtaggart/repos\", \"events_url\": \"https://api.github.com/users/noahtaggart/events{/privacy}\", \"received_events_url\": \"https://api.github.com/users/noahtaggart/received_events\", \"type\": \"User\", \"site_admin\": false, \"name\": \"Noah Taggart\", \"company\": null, \"blog\": \"\", \"location\": \"Nashville, TN\", \"email\": null, \"hireable\": null, \"bio\": null, \"twitter_username\": null, \"public_repos\": 0, \"public_gists\": 0, \"followers\": 0, \"following\": 0, \"created_at\": \"2021-12-27T04:59:53Z\", \"updated_at\": \"2022-01-06T15:10:58Z\"}"
        }
    },
    {
        "model": "socialaccount.socialaccount",
        "pk": 15,
        "fields": {
            "user": 22,
            "provider": "github",
            "uid": "31977862",
            "last_login": "2022-01-06T15:11:57.342Z",
            "date_joined": "2022-01-06T15:05:54.424Z",
            "extra_data": "{\"login\": \"DarthTayder\", \"id\": 31977862, \"node_id\": \"MDQ6VXNlcjMxOTc3ODYy\", \"avatar_url\": \"https://avatars.githubusercontent.com/u/31977862?v=4\", \"gravatar_id\": \"\", \"url\": \"https://api.github.com/users/DarthTayder\", \"html_url\": \"https://github.com/DarthTayder\", \"followers_url\": \"https://api.github.com/users/DarthTayder/followers\", \"following_url\": \"https://api.github.com/users/DarthTayder/following{/other_user}\", \"gists_url\": \"https://api.github.com/users/DarthTayder/gists{/gist_id}\", \"starred_url\": \"https://api.github.com/users/DarthTayder/starred{/owner}{/repo}\", \"subscriptions_url\": \"https://api.github.com/users/DarthTayder/subscriptions\", \"organizations_url\": \"https://api.github.com/users/DarthTayder/orgs\", \"repos_url\": \"https://api.github.com/users/DarthTayder/repos\", \"events_url\": \"https://api.github.com/users/DarthTayder/events{/privacy}\", \"received_events_url\": \"https://api.github.com/users/DarthTayder/received_events\", \"type\": \"User\", \"site_admin\": false, \"name\": \"Taylor Stephenson\", \"company\": null, \"blog\": \"\", \"location\": null, \"email\": null, \"hireable\": null, \"bio\": null, \"twitter_username\": null, \"public_repos\": 0, \"public_gists\": 0, \"followers\": 0, \"following\": 0, \"created_at\": \"2017-09-15T03:17:00Z\", \"updated_at\": \"2022-01-06T15:08:15Z\"}"
        }
    },
    {
        "model": "socialaccount.socialaccount",
        "pk": 16,
        "fields": {
            "user": 23,
            "provider": "github",
            "uid": "91293171",
            "last_login": "2022-01-06T15:11:58.105Z",
            "date_joined": "2022-01-06T15:05:54.904Z",
            "extra_data": "{\"login\": \"AriDaron\", \"id\": 91293171, \"node_id\": \"MDQ6VXNlcjkxMjkzMTcx\", \"avatar_url\": \"https://avatars.githubusercontent.com/u/91293171?v=4\", \"gravatar_id\": \"\", \"url\": \"https://api.github.com/users/AriDaron\", \"html_url\": \"https://github.com/AriDaron\", \"followers_url\": \"https://api.github.com/users/AriDaron/followers\", \"following_url\": \"https://api.github.com/users/AriDaron/following{/other_user}\", \"gists_url\": \"https://api.github.com/users/AriDaron/gists{/gist_id}\", \"starred_url\": \"https://api.github.com/users/AriDaron/starred{/owner}{/repo}\", \"subscriptions_url\": \"https://api.github.com/users/AriDaron/subscriptions\", \"organizations_url\": \"https://api.github.com/users/AriDaron/orgs\", \"repos_url\": \"https://api.github.com/users/AriDaron/repos\", \"events_url\": \"https://api.github.com/users/AriDaron/events{/privacy}\", \"received_events_url\": \"https://api.github.com/users/AriDaron/received_events\", \"type\": \"User\", \"site_admin\": false, \"name\": \"Arielle Daron\", \"company\": null, \"blog\": \"\", \"location\": null, \"email\": null, \"hireable\": null, \"bio\": null, \"twitter_username\": null, \"public_repos\": 9, \"public_gists\": 0, \"followers\": 0, \"following\": 0, \"created_at\": \"2021-09-23T22:27:50Z\", \"updated_at\": \"2022-01-06T15:08:20Z\"}"
        }
    },
    {
        "model": "socialaccount.socialaccount",
        "pk": 17,
        "fields": {
            "user": 24,
            "provider": "github",
            "uid": "62916330",
            "last_login": "2022-01-06T15:05:55.425Z",
            "date_joined": "2022-01-06T15:05:55.426Z",
            "extra_data": "{\"login\": \"Juulo\", \"id\": 62916330, \"node_id\": \"MDQ6VXNlcjYyOTE2MzMw\", \"avatar_url\": \"https://avatars.githubusercontent.com/u/62916330?v=4\", \"gravatar_id\": \"\", \"url\": \"https://api.github.com/users/Juulo\", \"html_url\": \"https://github.com/Juulo\", \"followers_url\": \"https://api.github.com/users/Juulo/followers\", \"following_url\": \"https://api.github.com/users/Juulo/following{/other_user}\", \"gists_url\": \"https://api.github.com/users/Juulo/gists{/gist_id}\", \"starred_url\": \"https://api.github.com/users/Juulo/starred{/owner}{/repo}\", \"subscriptions_url\": \"https://api.github.com/users/Juulo/subscriptions\", \"organizations_url\": \"https://api.github.com/users/Juulo/orgs\", \"repos_url\": \"https://api.github.com/users/Juulo/repos\", \"events_url\": \"https://api.github.com/users/Juulo/events{/privacy}\", \"received_events_url\": \"https://api.github.com/users/Juulo/received_events\", \"type\": \"User\", \"site_admin\": false, \"name\": null, \"company\": null, \"blog\": \"\", \"location\": null, \"email\": null, \"hireable\": null, \"bio\": null, \"twitter_username\": null, \"public_repos\": 4, \"public_gists\": 0, \"followers\": 0, \"following\": 0, \"created_at\": \"2020-03-31T00:20:57Z\", \"updated_at\": \"2021-09-01T16:15:54Z\"}"
        }
    },
    {
        "model": "socialaccount.socialaccount",
        "pk": 18,
        "fields": {
            "user": 25,
            "provider": "github",
            "uid": "97056756",
            "last_login": "2022-01-06T15:12:01.663Z",
            "date_joined": "2022-01-06T15:05:56.597Z",
            "extra_data": "{\"login\": \"shaner0892\", \"id\": 97056756, \"node_id\": \"U_kgDOBcj39A\", \"avatar_url\": \"https://avatars.githubusercontent.com/u/97056756?v=4\", \"gravatar_id\": \"\", \"url\": \"https://api.github.com/users/shaner0892\", \"html_url\": \"https://github.com/shaner0892\", \"followers_url\": \"https://api.github.com/users/shaner0892/followers\", \"following_url\": \"https://api.github.com/users/shaner0892/following{/other_user}\", \"gists_url\": \"https://api.github.com/users/shaner0892/gists{/gist_id}\", \"starred_url\": \"https://api.github.com/users/shaner0892/starred{/owner}{/repo}\", \"subscriptions_url\": \"https://api.github.com/users/shaner0892/subscriptions\", \"organizations_url\": \"https://api.github.com/users/shaner0892/orgs\", \"repos_url\": \"https://api.github.com/users/shaner0892/repos\", \"events_url\": \"https://api.github.com/users/shaner0892/events{/privacy}\", \"received_events_url\": \"https://api.github.com/users/shaner0892/received_events\", \"type\": \"User\", \"site_admin\": false, \"name\": \"Hilary Shaner\", \"company\": null, \"blog\": \"\", \"location\": null, \"email\": null, \"hireable\": null, \"bio\": null, \"twitter_username\": null, \"public_repos\": 0, \"public_gists\": 0, \"followers\": 0, \"following\": 0, \"created_at\": \"2022-01-03T19:11:38Z\", \"updated_at\": \"2022-01-06T15:10:35Z\"}"
        }
    },
    {
        "model": "socialaccount.socialaccount",
        "pk": 19,
        "fields": {
            "user": 26,
            "provider": "github",
            "uid": "97056303",
            "last_login": "2022-01-06T15:12:02.842Z",
            "date_joined": "2022-01-06T15:05:57.633Z",
            "extra_data": "{\"login\": \"katiemdawkins\", \"id\": 97056303, \"node_id\": \"U_kgDOBcj2Lw\", \"avatar_url\": \"https://avatars.githubusercontent.com/u/97056303?v=4\", \"gravatar_id\": \"\", \"url\": \"https://api.github.com/users/katiemdawkins\", \"html_url\": \"https://github.com/katiemdawkins\", \"followers_url\": \"https://api.github.com/users/katiemdawkins/followers\", \"following_url\": \"https://api.github.com/users/katiemdawkins/following{/other_user}\", \"gists_url\": \"https://api.github.com/users/katiemdawkins/gists{/gist_id}\", \"starred_url\": \"https://api.github.com/users/katiemdawkins/starred{/owner}{/repo}\", \"subscriptions_url\": \"https://api.github.com/users/katiemdawkins/subscriptions\", \"organizations_url\": \"https://api.github.com/users/katiemdawkins/orgs\", \"repos_url\": \"https://api.github.com/users/katiemdawkins/repos\", \"events_url\": \"https://api.github.com/users/katiemdawkins/events{/privacy}\", \"received_events_url\": \"https://api.github.com/users/katiemdawkins/received_events\", \"type\": \"User\", \"site_admin\": false, \"name\": \"Katie Dawkins\", \"company\": null, \"blog\": \"\", \"location\": null, \"email\": null, \"hireable\": null, \"bio\": null, \"twitter_username\": null, \"public_repos\": 0, \"public_gists\": 0, \"followers\": 0, \"following\": 0, \"created_at\": \"2022-01-03T19:09:11Z\", \"updated_at\": \"2022-01-06T15:08:26Z\"}"
        }
    },
    {
        "model": "socialaccount.socialaccount",
        "pk": 20,
        "fields": {
            "user": 27,
            "provider": "github",
            "uid": "10354411",
            "last_login": "2022-01-10T14:54:40.496Z",
            "date_joined": "2022-01-06T15:05:57.792Z",
            "extra_data": "{\"login\": \"gregoryhaney\", \"id\": 10354411, \"node_id\": \"MDQ6VXNlcjEwMzU0NDEx\", \"avatar_url\": \"https://avatars.githubusercontent.com/u/10354411?v=4\", \"gravatar_id\": \"\", \"url\": \"https://api.github.com/users/gregoryhaney\", \"html_url\": \"https://github.com/gregoryhaney\", \"followers_url\": \"https://api.github.com/users/gregoryhaney/followers\", \"following_url\": \"https://api.github.com/users/gregoryhaney/following{/other_user}\", \"gists_url\": \"https://api.github.com/users/gregoryhaney/gists{/gist_id}\", \"starred_url\": \"https://api.github.com/users/gregoryhaney/starred{/owner}{/repo}\", \"subscriptions_url\": \"https://api.github.com/users/gregoryhaney/subscriptions\", \"organizations_url\": \"https://api.github.com/users/gregoryhaney/orgs\", \"repos_url\": \"https://api.github.com/users/gregoryhaney/repos\", \"events_url\": \"https://api.github.com/users/gregoryhaney/events{/privacy}\", \"received_events_url\": \"https://api.github.com/users/gregoryhaney/received_events\", \"type\": \"User\", \"site_admin\": false, \"name\": \"Gregory Haney\", \"company\": null, \"blog\": \"\", \"location\": \"Nashville, Tennessee, USA\", \"email\": \"gregory.haney@gmail.com\", \"hireable\": null, \"bio\": null, \"twitter_username\": null, \"public_repos\": 8, \"public_gists\": 0, \"followers\": 0, \"following\": 0, \"created_at\": \"2014-12-31T02:17:17Z\", \"updated_at\": \"2022-01-09T15:51:02Z\"}"
        }
    },
    {
        "model": "socialaccount.socialaccount",
        "pk": 21,
        "fields": {
            "user": 28,
            "provider": "github",
            "uid": "94871164",
            "last_login": "2022-01-06T15:12:10.862Z",
            "date_joined": "2022-01-06T15:06:01.895Z",
            "extra_data": "{\"login\": \"JakeBrooks98\", \"id\": 94871164, \"node_id\": \"U_kgDOBaeefA\", \"avatar_url\": \"https://avatars.githubusercontent.com/u/94871164?v=4\", \"gravatar_id\": \"\", \"url\": \"https://api.github.com/users/JakeBrooks98\", \"html_url\": \"https://github.com/JakeBrooks98\", \"followers_url\": \"https://api.github.com/users/JakeBrooks98/followers\", \"following_url\": \"https://api.github.com/users/JakeBrooks98/following{/other_user}\", \"gists_url\": \"https://api.github.com/users/JakeBrooks98/gists{/gist_id}\", \"starred_url\": \"https://api.github.com/users/JakeBrooks98/starred{/owner}{/repo}\", \"subscriptions_url\": \"https://api.github.com/users/JakeBrooks98/subscriptions\", \"organizations_url\": \"https://api.github.com/users/JakeBrooks98/orgs\", \"repos_url\": \"https://api.github.com/users/JakeBrooks98/repos\", \"events_url\": \"https://api.github.com/users/JakeBrooks98/events{/privacy}\", \"received_events_url\": \"https://api.github.com/users/JakeBrooks98/received_events\", \"type\": \"User\", \"site_admin\": false, \"name\": \"Jake Brooks\", \"company\": null, \"blog\": \"\", \"location\": null, \"email\": null, \"hireable\": null, \"bio\": null, \"twitter_username\": null, \"public_repos\": 0, \"public_gists\": 0, \"followers\": 0, \"following\": 0, \"created_at\": \"2021-11-22T21:12:16Z\", \"updated_at\": \"2022-01-06T15:08:39Z\"}"
        }
    },
    {
        "model": "socialaccount.socialaccount",
        "pk": 22,
        "fields": {
            "user": 29,
            "provider": "github",
            "uid": "97055138",
            "last_login": "2022-01-06T16:46:48.456Z",
            "date_joined": "2022-01-06T15:06:04.558Z",
            "extra_data": "{\"login\": \"ehils\", \"id\": 97055138, \"node_id\": \"U_kgDOBcjxog\", \"avatar_url\": \"https://avatars.githubusercontent.com/u/97055138?v=4\", \"gravatar_id\": \"\", \"url\": \"https://api.github.com/users/ehils\", \"html_url\": \"https://github.com/ehils\", \"followers_url\": \"https://api.github.com/users/ehils/followers\", \"following_url\": \"https://api.github.com/users/ehils/following{/other_user}\", \"gists_url\": \"https://api.github.com/users/ehils/gists{/gist_id}\", \"starred_url\": \"https://api.github.com/users/ehils/starred{/owner}{/repo}\", \"subscriptions_url\": \"https://api.github.com/users/ehils/subscriptions\", \"organizations_url\": \"https://api.github.com/users/ehils/orgs\", \"repos_url\": \"https://api.github.com/users/ehils/repos\", \"events_url\": \"https://api.github.com/users/ehils/events{/privacy}\", \"received_events_url\": \"https://api.github.com/users/ehils/received_events\", \"type\": \"User\", \"site_admin\": false, \"name\": \"Erich Hils\", \"company\": null, \"blog\": \"\", \"location\": null, \"email\": null, \"hireable\": null, \"bio\": null, \"twitter_username\": null, \"public_repos\": 0, \"public_gists\": 0, \"followers\": 0, \"following\": 0, \"created_at\": \"2022-01-03T18:41:58Z\", \"updated_at\": \"2022-01-06T15:12:22Z\"}"
        }
    },
    {
        "model": "socialaccount.socialaccount",
        "pk": 23,
        "fields": {
            "user": 30,
            "provider": "github",
            "uid": "69877108",
            "last_login": "2022-01-06T15:12:00.240Z",
            "date_joined": "2022-01-06T15:06:04.626Z",
            "extra_data": "{\"login\": \"wwardrop3\", \"id\": 69877108, \"node_id\": \"MDQ6VXNlcjY5ODc3MTA4\", \"avatar_url\": \"https://avatars.githubusercontent.com/u/69877108?v=4\", \"gravatar_id\": \"\", \"url\": \"https://api.github.com/users/wwardrop3\", \"html_url\": \"https://github.com/wwardrop3\", \"followers_url\": \"https://api.github.com/users/wwardrop3/followers\", \"following_url\": \"https://api.github.com/users/wwardrop3/following{/other_user}\", \"gists_url\": \"https://api.github.com/users/wwardrop3/gists{/gist_id}\", \"starred_url\": \"https://api.github.com/users/wwardrop3/starred{/owner}{/repo}\", \"subscriptions_url\": \"https://api.github.com/users/wwardrop3/subscriptions\", \"organizations_url\": \"https://api.github.com/users/wwardrop3/orgs\", \"repos_url\": \"https://api.github.com/users/wwardrop3/repos\", \"events_url\": \"https://api.github.com/users/wwardrop3/events{/privacy}\", \"received_events_url\": \"https://api.github.com/users/wwardrop3/received_events\", \"type\": \"User\", \"site_admin\": false, \"name\": \"Will Wardrop\", \"company\": null, \"blog\": \"\", \"location\": null, \"email\": null, \"hireable\": null, \"bio\": null, \"twitter_username\": null, \"public_repos\": 0, \"public_gists\": 0, \"followers\": 0, \"following\": 0, \"created_at\": \"2020-08-18T23:00:16Z\", \"updated_at\": \"2022-01-06T15:09:30Z\"}"
        }
    },
    {
        "model": "socialaccount.socialaccount",
        "pk": 24,
        "fields": {
            "user": 31,
            "provider": "github",
            "uid": "96555058",
            "last_login": "2022-01-06T15:12:01.418Z",
            "date_joined": "2022-01-06T15:06:04.973Z",
            "extra_data": "{\"login\": \"jmehart\", \"id\": 96555058, \"node_id\": \"U_kgDOBcFQMg\", \"avatar_url\": \"https://avatars.githubusercontent.com/u/96555058?v=4\", \"gravatar_id\": \"\", \"url\": \"https://api.github.com/users/jmehart\", \"html_url\": \"https://github.com/jmehart\", \"followers_url\": \"https://api.github.com/users/jmehart/followers\", \"following_url\": \"https://api.github.com/users/jmehart/following{/other_user}\", \"gists_url\": \"https://api.github.com/users/jmehart/gists{/gist_id}\", \"starred_url\": \"https://api.github.com/users/jmehart/starred{/owner}{/repo}\", \"subscriptions_url\": \"https://api.github.com/users/jmehart/subscriptions\", \"organizations_url\": \"https://api.github.com/users/jmehart/orgs\", \"repos_url\": \"https://api.github.com/users/jmehart/repos\", \"events_url\": \"https://api.github.com/users/jmehart/events{/privacy}\", \"received_events_url\": \"https://api.github.com/users/jmehart/received_events\", \"type\": \"User\", \"site_admin\": false, \"name\": \"Jaimie Hart\", \"company\": null, \"blog\": \"\", \"location\": null, \"email\": null, \"hireable\": null, \"bio\": null, \"twitter_username\": null, \"public_repos\": 0, \"public_gists\": 0, \"followers\": 0, \"following\": 0, \"created_at\": \"2021-12-23T00:58:40Z\", \"updated_at\": \"2021-12-23T03:08:31Z\"}"
        }
    },
    {
        "model": "socialaccount.socialaccount",
        "pk": 25,
        "fields": {
            "user": 32,
            "provider": "github",
            "uid": "97034818",
            "last_login": "2022-01-06T16:38:58.009Z",
            "date_joined": "2022-01-06T15:06:05.355Z",
            "extra_data": "{\"login\": \"Kjcaruso12\", \"id\": 97034818, \"node_id\": \"U_kgDOBciiQg\", \"avatar_url\": \"https://avatars.githubusercontent.com/u/97034818?v=4\", \"gravatar_id\": \"\", \"url\": \"https://api.github.com/users/Kjcaruso12\", \"html_url\": \"https://github.com/Kjcaruso12\", \"followers_url\": \"https://api.github.com/users/Kjcaruso12/followers\", \"following_url\": \"https://api.github.com/users/Kjcaruso12/following{/other_user}\", \"gists_url\": \"https://api.github.com/users/Kjcaruso12/gists{/gist_id}\", \"starred_url\": \"https://api.github.com/users/Kjcaruso12/starred{/owner}{/repo}\", \"subscriptions_url\": \"https://api.github.com/users/Kjcaruso12/subscriptions\", \"organizations_url\": \"https://api.github.com/users/Kjcaruso12/orgs\", \"repos_url\": \"https://api.github.com/users/Kjcaruso12/repos\", \"events_url\": \"https://api.github.com/users/Kjcaruso12/events{/privacy}\", \"received_events_url\": \"https://api.github.com/users/Kjcaruso12/received_events\", \"type\": \"User\", \"site_admin\": false, \"name\": \"Kevin Caruso\", \"company\": null, \"blog\": \"\", \"location\": null, \"email\": null, \"hireable\": null, \"bio\": null, \"twitter_username\": null, \"public_repos\": 0, \"public_gists\": 0, \"followers\": 0, \"following\": 0, \"created_at\": \"2022-01-03T13:27:34Z\", \"updated_at\": \"2022-01-06T15:08:14Z\"}"
        }
    },
    {
        "model": "socialaccount.socialaccount",
        "pk": 26,
        "fields": {
            "user": 33,
            "provider": "github",
            "uid": "97057467",
            "last_login": "2022-01-06T15:12:08.470Z",
            "date_joined": "2022-01-06T15:06:05.886Z",
            "extra_data": "{\"login\": \"olichtenstein1\", \"id\": 97057467, \"node_id\": \"U_kgDOBcj6uw\", \"avatar_url\": \"https://avatars.githubusercontent.com/u/97057467?v=4\", \"gravatar_id\": \"\", \"url\": \"https://api.github.com/users/olichtenstein1\", \"html_url\": \"https://github.com/olichtenstein1\", \"followers_url\": \"https://api.github.com/users/olichtenstein1/followers\", \"following_url\": \"https://api.github.com/users/olichtenstein1/following{/other_user}\", \"gists_url\": \"https://api.github.com/users/olichtenstein1/gists{/gist_id}\", \"starred_url\": \"https://api.github.com/users/olichtenstein1/starred{/owner}{/repo}\", \"subscriptions_url\": \"https://api.github.com/users/olichtenstein1/subscriptions\", \"organizations_url\": \"https://api.github.com/users/olichtenstein1/orgs\", \"repos_url\": \"https://api.github.com/users/olichtenstein1/repos\", \"events_url\": \"https://api.github.com/users/olichtenstein1/events{/privacy}\", \"received_events_url\": \"https://api.github.com/users/olichtenstein1/received_events\", \"type\": \"User\", \"site_admin\": false, \"name\": \"Ollie Lichtenstein\", \"company\": null, \"blog\": \"\", \"location\": null, \"email\": null, \"hireable\": null, \"bio\": null, \"twitter_username\": null, \"public_repos\": 0, \"public_gists\": 0, \"followers\": 0, \"following\": 0, \"created_at\": \"2022-01-03T19:16:12Z\", \"updated_at\": \"2022-01-06T15:08:14Z\"}"
        }
    },
    {
        "model": "socialaccount.socialaccount",
        "pk": 27,
        "fields": {
            "user": 34,
            "provider": "github",
            "uid": "96503963",
            "last_login": "2022-01-06T15:12:03.106Z",
            "date_joined": "2022-01-06T15:06:06.573Z",
            "extra_data": "{\"login\": \"steviehollander\", \"id\": 96503963, \"node_id\": \"U_kgDOBcCImw\", \"avatar_url\": \"https://avatars.githubusercontent.com/u/96503963?v=4\", \"gravatar_id\": \"\", \"url\": \"https://api.github.com/users/steviehollander\", \"html_url\": \"https://github.com/steviehollander\", \"followers_url\": \"https://api.github.com/users/steviehollander/followers\", \"following_url\": \"https://api.github.com/users/steviehollander/following{/other_user}\", \"gists_url\": \"https://api.github.com/users/steviehollander/gists{/gist_id}\", \"starred_url\": \"https://api.github.com/users/steviehollander/starred{/owner}{/repo}\", \"subscriptions_url\": \"https://api.github.com/users/steviehollander/subscriptions\", \"organizations_url\": \"https://api.github.com/users/steviehollander/orgs\", \"repos_url\": \"https://api.github.com/users/steviehollander/repos\", \"events_url\": \"https://api.github.com/users/steviehollander/events{/privacy}\", \"received_events_url\": \"https://api.github.com/users/steviehollander/received_events\", \"type\": \"User\", \"site_admin\": false, \"name\": \"Stevie Hollander\", \"company\": null, \"blog\": \"\", \"location\": null, \"email\": null, \"hireable\": null, \"bio\": null, \"twitter_username\": null, \"public_repos\": 1, \"public_gists\": 0, \"followers\": 0, \"following\": 0, \"created_at\": \"2021-12-21T23:48:25Z\", \"updated_at\": \"2022-01-06T15:08:17Z\"}"
        }
    },
    {
        "model": "socialaccount.socialaccount",
        "pk": 28,
        "fields": {
            "user": 35,
            "provider": "github",
            "uid": "96551414",
            "last_login": "2022-01-06T15:12:13.767Z",
            "date_joined": "2022-01-06T15:06:07.557Z",
            "extra_data": "{\"login\": \"Airriswilliams\", \"id\": 96551414, \"node_id\": \"U_kgDOBcFB9g\", \"avatar_url\": \"https://avatars.githubusercontent.com/u/96551414?v=4\", \"gravatar_id\": \"\", \"url\": \"https://api.github.com/users/Airriswilliams\", \"html_url\": \"https://github.com/Airriswilliams\", \"followers_url\": \"https://api.github.com/users/Airriswilliams/followers\", \"following_url\": \"https://api.github.com/users/Airriswilliams/following{/other_user}\", \"gists_url\": \"https://api.github.com/users/Airriswilliams/gists{/gist_id}\", \"starred_url\": \"https://api.github.com/users/Airriswilliams/starred{/owner}{/repo}\", \"subscriptions_url\": \"https://api.github.com/users/Airriswilliams/subscriptions\", \"organizations_url\": \"https://api.github.com/users/Airriswilliams/orgs\", \"repos_url\": \"https://api.github.com/users/Airriswilliams/repos\", \"events_url\": \"https://api.github.com/users/Airriswilliams/events{/privacy}\", \"received_events_url\": \"https://api.github.com/users/Airriswilliams/received_events\", \"type\": \"User\", \"site_admin\": false, \"name\": \"Airris Williams\", \"company\": null, \"blog\": \"\", \"location\": null, \"email\": null, \"hireable\": null, \"bio\": null, \"twitter_username\": null, \"public_repos\": 0, \"public_gists\": 0, \"followers\": 0, \"following\": 0, \"created_at\": \"2021-12-22T22:03:33Z\", \"updated_at\": \"2022-01-06T15:11:46Z\"}"
        }
    },
    {
        "model": "socialaccount.socialaccount",
        "pk": 29,
        "fields": {
            "user": 36,
            "provider": "github",
            "uid": "96992803",
            "last_login": "2022-01-06T18:54:47.825Z",
            "date_joined": "2022-01-06T15:06:07.775Z",
            "extra_data": "{\"login\": \"LaudenEller\", \"id\": 96992803, \"node_id\": \"U_kgDOBcf-Iw\", \"avatar_url\": \"https://avatars.githubusercontent.com/u/96992803?v=4\", \"gravatar_id\": \"\", \"url\": \"https://api.github.com/users/LaudenEller\", \"html_url\": \"https://github.com/LaudenEller\", \"followers_url\": \"https://api.github.com/users/LaudenEller/followers\", \"following_url\": \"https://api.github.com/users/LaudenEller/following{/other_user}\", \"gists_url\": \"https://api.github.com/users/LaudenEller/gists{/gist_id}\", \"starred_url\": \"https://api.github.com/users/LaudenEller/starred{/owner}{/repo}\", \"subscriptions_url\": \"https://api.github.com/users/LaudenEller/subscriptions\", \"organizations_url\": \"https://api.github.com/users/LaudenEller/orgs\", \"repos_url\": \"https://api.github.com/users/LaudenEller/repos\", \"events_url\": \"https://api.github.com/users/LaudenEller/events{/privacy}\", \"received_events_url\": \"https://api.github.com/users/LaudenEller/received_events\", \"type\": \"User\", \"site_admin\": false, \"name\": \"Lauden Eller\", \"company\": null, \"blog\": \"\", \"location\": null, \"email\": null, \"hireable\": null, \"bio\": null, \"twitter_username\": null, \"public_repos\": 2, \"public_gists\": 0, \"followers\": 0, \"following\": 0, \"created_at\": \"2022-01-02T17:33:50Z\", \"updated_at\": \"2022-01-06T15:09:02Z\"}"
        }
    },
    {
        "model": "socialaccount.socialaccount",
        "pk": 30,
        "fields": {
            "user": 37,
            "provider": "github",
            "uid": "96600790",
            "last_login": "2022-01-06T16:43:58.008Z",
            "date_joined": "2022-01-06T15:06:12.752Z",
            "extra_data": "{\"login\": \"VanNg76\", \"id\": 96600790, \"node_id\": \"U_kgDOBcIC1g\", \"avatar_url\": \"https://avatars.githubusercontent.com/u/96600790?v=4\", \"gravatar_id\": \"\", \"url\": \"https://api.github.com/users/VanNg76\", \"html_url\": \"https://github.com/VanNg76\", \"followers_url\": \"https://api.github.com/users/VanNg76/followers\", \"following_url\": \"https://api.github.com/users/VanNg76/following{/other_user}\", \"gists_url\": \"https://api.github.com/users/VanNg76/gists{/gist_id}\", \"starred_url\": \"https://api.github.com/users/VanNg76/starred{/owner}{/repo}\", \"subscriptions_url\": \"https://api.github.com/users/VanNg76/subscriptions\", \"organizations_url\": \"https://api.github.com/users/VanNg76/orgs\", \"repos_url\": \"https://api.github.com/users/VanNg76/repos\", \"events_url\": \"https://api.github.com/users/VanNg76/events{/privacy}\", \"received_events_url\": \"https://api.github.com/users/VanNg76/received_events\", \"type\": \"User\", \"site_admin\": false, \"name\": \"Van Nguyen\", \"company\": null, \"blog\": \"\", \"location\": null, \"email\": null, \"hireable\": null, \"bio\": null, \"twitter_username\": null, \"public_repos\": 0, \"public_gists\": 0, \"followers\": 0, \"following\": 0, \"created_at\": \"2021-12-23T23:55:40Z\", \"updated_at\": \"2022-01-06T15:08:19Z\"}"
        }
    },
    {
        "model": "socialaccount.socialaccount",
        "pk": 31,
        "fields": {
            "user": 38,
            "provider": "github",
            "uid": "96610746",
            "last_login": "2022-01-06T15:12:01.950Z",
            "date_joined": "2022-01-06T15:06:18.207Z",
            "extra_data": "{\"login\": \"RussellCall\", \"id\": 96610746, \"node_id\": \"U_kgDOBcIpug\", \"avatar_url\": \"https://avatars.githubusercontent.com/u/96610746?v=4\", \"gravatar_id\": \"\", \"url\": \"https://api.github.com/users/RussellCall\", \"html_url\": \"https://github.com/RussellCall\", \"followers_url\": \"https://api.github.com/users/RussellCall/followers\", \"following_url\": \"https://api.github.com/users/RussellCall/following{/other_user}\", \"gists_url\": \"https://api.github.com/users/RussellCall/gists{/gist_id}\", \"starred_url\": \"https://api.github.com/users/RussellCall/starred{/owner}{/repo}\", \"subscriptions_url\": \"https://api.github.com/users/RussellCall/subscriptions\", \"organizations_url\": \"https://api.github.com/users/RussellCall/orgs\", \"repos_url\": \"https://api.github.com/users/RussellCall/repos\", \"events_url\": \"https://api.github.com/users/RussellCall/events{/privacy}\", \"received_events_url\": \"https://api.github.com/users/RussellCall/received_events\", \"type\": \"User\", \"site_admin\": false, \"name\": \"Russell Call\", \"company\": null, \"blog\": \"\", \"location\": null, \"email\": null, \"hireable\": null, \"bio\": null, \"twitter_username\": null, \"public_repos\": 0, \"public_gists\": 0, \"followers\": 0, \"following\": 0, \"created_at\": \"2021-12-24T06:41:38Z\", \"updated_at\": \"2022-01-06T15:08:27Z\"}"
        }
    },
    {
        "model": "socialaccount.socialaccount",
        "pk": 32,
        "fields": {
            "user": 39,
            "provider": "github",
            "uid": "88666197",
            "last_login": "2022-01-06T15:58:06.047Z",
            "date_joined": "2022-01-06T15:06:22.811Z",
            "extra_data": "{\"login\": \"IyannaF\", \"id\": 88666197, \"node_id\": \"MDQ6VXNlcjg4NjY2MTk3\", \"avatar_url\": \"https://avatars.githubusercontent.com/u/88666197?v=4\", \"gravatar_id\": \"\", \"url\": \"https://api.github.com/users/IyannaF\", \"html_url\": \"https://github.com/IyannaF\", \"followers_url\": \"https://api.github.com/users/IyannaF/followers\", \"following_url\": \"https://api.github.com/users/IyannaF/following{/other_user}\", \"gists_url\": \"https://api.github.com/users/IyannaF/gists{/gist_id}\", \"starred_url\": \"https://api.github.com/users/IyannaF/starred{/owner}{/repo}\", \"subscriptions_url\": \"https://api.github.com/users/IyannaF/subscriptions\", \"organizations_url\": \"https://api.github.com/users/IyannaF/orgs\", \"repos_url\": \"https://api.github.com/users/IyannaF/repos\", \"events_url\": \"https://api.github.com/users/IyannaF/events{/privacy}\", \"received_events_url\": \"https://api.github.com/users/IyannaF/received_events\", \"type\": \"User\", \"site_admin\": false, \"name\": \"Iyanna Forbes\", \"company\": null, \"blog\": \"\", \"location\": null, \"email\": null, \"hireable\": null, \"bio\": null, \"twitter_username\": null, \"public_repos\": 3, \"public_gists\": 0, \"followers\": 0, \"following\": 0, \"created_at\": \"2021-08-09T13:03:43Z\", \"updated_at\": \"2022-01-06T15:08:24Z\"}"
        }
    },
    {
        "model": "socialaccount.socialaccount",
        "pk": 33,
        "fields": {
            "user": 40,
            "provider": "github",
            "uid": "42020876",
            "last_login": "2022-01-06T15:12:21.491Z",
            "date_joined": "2022-01-06T15:06:22.854Z",
            "extra_data": "{\"login\": \"laurabethmaddox\", \"id\": 42020876, \"node_id\": \"MDQ6VXNlcjQyMDIwODc2\", \"avatar_url\": \"https://avatars.githubusercontent.com/u/42020876?v=4\", \"gravatar_id\": \"\", \"url\": \"https://api.github.com/users/laurabethmaddox\", \"html_url\": \"https://github.com/laurabethmaddox\", \"followers_url\": \"https://api.github.com/users/laurabethmaddox/followers\", \"following_url\": \"https://api.github.com/users/laurabethmaddox/following{/other_user}\", \"gists_url\": \"https://api.github.com/users/laurabethmaddox/gists{/gist_id}\", \"starred_url\": \"https://api.github.com/users/laurabethmaddox/starred{/owner}{/repo}\", \"subscriptions_url\": \"https://api.github.com/users/laurabethmaddox/subscriptions\", \"organizations_url\": \"https://api.github.com/users/laurabethmaddox/orgs\", \"repos_url\": \"https://api.github.com/users/laurabethmaddox/repos\", \"events_url\": \"https://api.github.com/users/laurabethmaddox/events{/privacy}\", \"received_events_url\": \"https://api.github.com/users/laurabethmaddox/received_events\", \"type\": \"User\", \"site_admin\": false, \"name\": \"Laura Beth Maddox\", \"company\": null, \"blog\": \"\", \"location\": null, \"email\": null, \"hireable\": null, \"bio\": null, \"twitter_username\": null, \"public_repos\": 0, \"public_gists\": 0, \"followers\": 1, \"following\": 0, \"created_at\": \"2018-08-02T04:31:53Z\", \"updated_at\": \"2022-01-06T15:08:43Z\"}"
        }
    },
    {
        "model": "socialaccount.socialaccount",
        "pk": 34,
        "fields": {
            "user": 41,
            "provider": "github",
            "uid": "96957033",
            "last_login": "2022-01-06T15:12:07.155Z",
            "date_joined": "2022-01-06T15:06:24.871Z",
            "extra_data": "{\"login\": \"donaghyam\", \"id\": 96957033, \"node_id\": \"U_kgDOBcdyaQ\", \"avatar_url\": \"https://avatars.githubusercontent.com/u/96957033?v=4\", \"gravatar_id\": \"\", \"url\": \"https://api.github.com/users/donaghyam\", \"html_url\": \"https://github.com/donaghyam\", \"followers_url\": \"https://api.github.com/users/donaghyam/followers\", \"following_url\": \"https://api.github.com/users/donaghyam/following{/other_user}\", \"gists_url\": \"https://api.github.com/users/donaghyam/gists{/gist_id}\", \"starred_url\": \"https://api.github.com/users/donaghyam/starred{/owner}{/repo}\", \"subscriptions_url\": \"https://api.github.com/users/donaghyam/subscriptions\", \"organizations_url\": \"https://api.github.com/users/donaghyam/orgs\", \"repos_url\": \"https://api.github.com/users/donaghyam/repos\", \"events_url\": \"https://api.github.com/users/donaghyam/events{/privacy}\", \"received_events_url\": \"https://api.github.com/users/donaghyam/received_events\", \"type\": \"User\", \"site_admin\": false, \"name\": \"Adam Donaghy\", \"company\": null, \"blog\": \"\", \"location\": null, \"email\": null, \"hireable\": null, \"bio\": null, \"twitter_username\": null, \"public_repos\": 0, \"public_gists\": 0, \"followers\": 0, \"following\": 0, \"created_at\": \"2022-01-01T20:10:23Z\", \"updated_at\": \"2022-01-06T15:08:18Z\"}"
        }
    },
    {
        "model": "socialaccount.socialaccount",
        "pk": 35,
        "fields": {
            "user": 42,
            "provider": "github",
            "uid": "96552912",
            "last_login": "2022-01-06T15:12:06.161Z",
            "date_joined": "2022-01-06T15:06:26.268Z",
            "extra_data": "{\"login\": \"grantbell1996\", \"id\": 96552912, \"node_id\": \"U_kgDOBcFH0A\", \"avatar_url\": \"https://avatars.githubusercontent.com/u/96552912?v=4\", \"gravatar_id\": \"\", \"url\": \"https://api.github.com/users/grantbell1996\", \"html_url\": \"https://github.com/grantbell1996\", \"followers_url\": \"https://api.github.com/users/grantbell1996/followers\", \"following_url\": \"https://api.github.com/users/grantbell1996/following{/other_user}\", \"gists_url\": \"https://api.github.com/users/grantbell1996/gists{/gist_id}\", \"starred_url\": \"https://api.github.com/users/grantbell1996/starred{/owner}{/repo}\", \"subscriptions_url\": \"https://api.github.com/users/grantbell1996/subscriptions\", \"organizations_url\": \"https://api.github.com/users/grantbell1996/orgs\", \"repos_url\": \"https://api.github.com/users/grantbell1996/repos\", \"events_url\": \"https://api.github.com/users/grantbell1996/events{/privacy}\", \"received_events_url\": \"https://api.github.com/users/grantbell1996/received_events\", \"type\": \"User\", \"site_admin\": false, \"name\": \"Grant Bell\", \"company\": null, \"blog\": \"\", \"location\": null, \"email\": null, \"hireable\": null, \"bio\": null, \"twitter_username\": null, \"public_repos\": 0, \"public_gists\": 0, \"followers\": 0, \"following\": 0, \"created_at\": \"2021-12-22T23:11:15Z\", \"updated_at\": \"2022-01-02T19:02:52Z\"}"
        }
    },
    {
        "model": "socialaccount.socialaccount",
        "pk": 36,
        "fields": {
            "user": 43,
            "provider": "github",
            "uid": "74992669",
            "last_login": "2022-01-06T17:10:32.660Z",
            "date_joined": "2022-01-06T15:06:36.955Z",
            "extra_data": "{\"login\": \"david-clark-1043\", \"id\": 74992669, \"node_id\": \"MDQ6VXNlcjc0OTkyNjY5\", \"avatar_url\": \"https://avatars.githubusercontent.com/u/74992669?v=4\", \"gravatar_id\": \"\", \"url\": \"https://api.github.com/users/david-clark-1043\", \"html_url\": \"https://github.com/david-clark-1043\", \"followers_url\": \"https://api.github.com/users/david-clark-1043/followers\", \"following_url\": \"https://api.github.com/users/david-clark-1043/following{/other_user}\", \"gists_url\": \"https://api.github.com/users/david-clark-1043/gists{/gist_id}\", \"starred_url\": \"https://api.github.com/users/david-clark-1043/starred{/owner}{/repo}\", \"subscriptions_url\": \"https://api.github.com/users/david-clark-1043/subscriptions\", \"organizations_url\": \"https://api.github.com/users/david-clark-1043/orgs\", \"repos_url\": \"https://api.github.com/users/david-clark-1043/repos\", \"events_url\": \"https://api.github.com/users/david-clark-1043/events{/privacy}\", \"received_events_url\": \"https://api.github.com/users/david-clark-1043/received_events\", \"type\": \"User\", \"site_admin\": false, \"name\": \"David Clark\", \"company\": null, \"blog\": \"\", \"location\": null, \"email\": null, \"hireable\": null, \"bio\": null, \"twitter_username\": null, \"public_repos\": 0, \"public_gists\": 0, \"followers\": 0, \"following\": 0, \"created_at\": \"2020-11-24T22:14:51Z\", \"updated_at\": \"2022-01-06T15:09:38Z\"}"
        }
    },
    {
        "model": "socialaccount.socialaccount",
        "pk": 37,
        "fields": {
            "user": 44,
            "provider": "github",
            "uid": "72361097",
            "last_login": "2022-01-06T15:12:05.502Z",
            "date_joined": "2022-01-06T15:06:49.829Z",
            "extra_data": "{\"login\": \"destinyfrith\", \"id\": 72361097, \"node_id\": \"MDQ6VXNlcjcyMzYxMDk3\", \"avatar_url\": \"https://avatars.githubusercontent.com/u/72361097?v=4\", \"gravatar_id\": \"\", \"url\": \"https://api.github.com/users/destinyfrith\", \"html_url\": \"https://github.com/destinyfrith\", \"followers_url\": \"https://api.github.com/users/destinyfrith/followers\", \"following_url\": \"https://api.github.com/users/destinyfrith/following{/other_user}\", \"gists_url\": \"https://api.github.com/users/destinyfrith/gists{/gist_id}\", \"starred_url\": \"https://api.github.com/users/destinyfrith/starred{/owner}{/repo}\", \"subscriptions_url\": \"https://api.github.com/users/destinyfrith/subscriptions\", \"organizations_url\": \"https://api.github.com/users/destinyfrith/orgs\", \"repos_url\": \"https://api.github.com/users/destinyfrith/repos\", \"events_url\": \"https://api.github.com/users/destinyfrith/events{/privacy}\", \"received_events_url\": \"https://api.github.com/users/destinyfrith/received_events\", \"type\": \"User\", \"site_admin\": false, \"name\": \"Destiny Frith\", \"company\": \"Destiny Frith\", \"blog\": \"\", \"location\": null, \"email\": null, \"hireable\": null, \"bio\": null, \"twitter_username\": null, \"public_repos\": 1, \"public_gists\": 0, \"followers\": 0, \"following\": 0, \"created_at\": \"2020-10-04T21:35:39Z\", \"updated_at\": \"2022-01-06T15:08:13Z\"}"
        }
    },
    {
        "model": "socialaccount.socialaccount",
        "pk": 38,
        "fields": {
            "user": 45,
            "provider": "github",
            "uid": "96592592",
            "last_login": "2022-01-06T15:12:04.779Z",
            "date_joined": "2022-01-06T15:08:45.724Z",
            "extra_data": "{\"login\": \"kristencarroll\", \"id\": 96592592, \"node_id\": \"U_kgDOBcHi0A\", \"avatar_url\": \"https://avatars.githubusercontent.com/u/96592592?v=4\", \"gravatar_id\": \"\", \"url\": \"https://api.github.com/users/kristencarroll\", \"html_url\": \"https://github.com/kristencarroll\", \"followers_url\": \"https://api.github.com/users/kristencarroll/followers\", \"following_url\": \"https://api.github.com/users/kristencarroll/following{/other_user}\", \"gists_url\": \"https://api.github.com/users/kristencarroll/gists{/gist_id}\", \"starred_url\": \"https://api.github.com/users/kristencarroll/starred{/owner}{/repo}\", \"subscriptions_url\": \"https://api.github.com/users/kristencarroll/subscriptions\", \"organizations_url\": \"https://api.github.com/users/kristencarroll/orgs\", \"repos_url\": \"https://api.github.com/users/kristencarroll/repos\", \"events_url\": \"https://api.github.com/users/kristencarroll/events{/privacy}\", \"received_events_url\": \"https://api.github.com/users/kristencarroll/received_events\", \"type\": \"User\", \"site_admin\": false, \"name\": \"Kristen Carroll\", \"company\": null, \"blog\": \"\", \"location\": null, \"email\": null, \"hireable\": null, \"bio\": null, \"twitter_username\": null, \"public_repos\": 0, \"public_gists\": 0, \"followers\": 0, \"following\": 0, \"created_at\": \"2021-12-23T18:09:19Z\", \"updated_at\": \"2022-01-06T15:08:22Z\"}"
        }
    },
    {
        "model": "socialaccount.socialaccount",
        "pk": 39,
        "fields": {
            "user": 46,
            "provider": "github",
            "uid": "16586839",
            "last_login": "2022-01-11T16:44:42.256Z",
            "date_joined": "2022-01-11T15:27:38.786Z",
            "extra_data": "{\"login\": \"dalamcd\", \"id\": 16586839, \"node_id\": \"MDQ6VXNlcjE2NTg2ODM5\", \"avatar_url\": \"https://avatars.githubusercontent.com/u/16586839?v=4\", \"gravatar_id\": \"\", \"url\": \"https://api.github.com/users/dalamcd\", \"html_url\": \"https://github.com/dalamcd\", \"followers_url\": \"https://api.github.com/users/dalamcd/followers\", \"following_url\": \"https://api.github.com/users/dalamcd/following{/other_user}\", \"gists_url\": \"https://api.github.com/users/dalamcd/gists{/gist_id}\", \"starred_url\": \"https://api.github.com/users/dalamcd/starred{/owner}{/repo}\", \"subscriptions_url\": \"https://api.github.com/users/dalamcd/subscriptions\", \"organizations_url\": \"https://api.github.com/users/dalamcd/orgs\", \"repos_url\": \"https://api.github.com/users/dalamcd/repos\", \"events_url\": \"https://api.github.com/users/dalamcd/events{/privacy}\", \"received_events_url\": \"https://api.github.com/users/dalamcd/received_events\", \"type\": \"User\", \"site_admin\": false, \"name\": null, \"company\": null, \"blog\": \"\", \"location\": null, \"email\": null, \"hireable\": null, \"bio\": null, \"twitter_username\": null, \"public_repos\": 30, \"public_gists\": 0, \"followers\": 3, \"following\": 0, \"created_at\": \"2016-01-07T03:59:46Z\", \"updated_at\": \"2021-06-29T00:47:35Z\"}"
        }
    },
    {
        "model": "socialaccount.socialtoken",
        "pk": 1,
        "fields": {
            "app": 1,
            "account": 1,
            "token": "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",
            "token_secret": "",
            "expires_at": null
        }
    },
    {
        "model": "socialaccount.socialtoken",
        "pk": 2,
        "fields": {
            "app": 1,
            "account": 2,
            "token": "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",
            "token_secret": "",
            "expires_at": null
        }
    },
    {
        "model": "socialaccount.socialtoken",
        "pk": 3,
        "fields": {
            "app": 1,
            "account": 3,
            "token": "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",
            "token_secret": "",
            "expires_at": null
        }
    },
    {
        "model": "socialaccount.socialtoken",
        "pk": 4,
        "fields": {
            "app": 1,
            "account": 4,
            "token": "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",
            "token_secret": "",
            "expires_at": null
        }
    },
    {
        "model": "socialaccount.socialtoken",
        "pk": 5,
        "fields": {
            "app": 1,
            "account": 5,
            "token": "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",
            "token_secret": "",
            "expires_at": null
        }
    },
    {
        "model": "socialaccount.socialtoken",
        "pk": 6,
        "fields": {
            "app": 1,
            "account": 6,
            "token": "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",
            "token_secret": "",
            "expires_at": null
        }
    },
    {
        "model": "socialaccount.socialtoken",
        "pk": 7,
        "fields": {
            "app": 1,
            "account": 7,
            "token": "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",
            "token_secret": "",
            "expires_at": null
        }
    },
    {
        "model": "socialaccount.socialtoken",
        "pk": 8,
        "fields": {
            "app": 1,
            "account": 8,
            "token": "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",
            "token_secret": "",
            "expires_at": null
        }
    },
    {
        "model": "socialaccount.socialtoken",
        "pk": 9,
        "fields": {
            "app": 1,
            "account": 9,
            "token": "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",
            "token_secret": "",
            "expires_at": null
        }
    },
    {
        "model": "socialaccount.socialtoken",
        "pk": 10,
        "fields": {
            "app": 1,
            "account": 10,
            "token": "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",
            "token_secret": "",
            "expires_at": null
        }
    },
    {
        "model": "socialaccount.socialtoken",
        "pk": 11,
        "fields": {
            "app": 1,
            "account": 11,
            "token": "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",
            "token_secret": "",
            "expires_at": null
        }
    },
    {
        "model": "socialaccount.socialtoken",
        "pk": 12,
        "fields": {
            "app": 1,
            "account": 12,
            "token": "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",
            "token_secret": "",
            "expires_at": null
        }
    },
    {
        "model": "socialaccount.socialtoken",
        "pk": 13,
        "fields": {
            "app": 1,
            "account": 13,
            "token": "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",
            "token_secret": "",
            "expires_at": null
        }
    },
    {
        "model": "socialaccount.socialtoken",
        "pk": 14,
        "fields": {
            "app": 1,
            "account": 14,
            "token": "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",
            "token_secret": "",
            "expires_at": null
        }
    },
    {
        "model": "socialaccount.socialtoken",
        "pk": 15,
        "fields": {
            "app": 1,
            "account": 15,
            "token": "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",
            "token_secret": "",
            "expires_at": null
        }
    },
    {
        "model": "socialaccount.socialtoken",
        "pk": 16,
        "fields": {
            "app": 1,
            "account": 16,
            "token": "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",
            "token_secret": "",
            "expires_at": null
        }
    },
    {
        "model": "socialaccount.socialtoken",
        "pk": 17,
        "fields": {
            "app": 1,
            "account": 17,
            "token": "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",
            "token_secret": "",
            "expires_at": null
        }
    },
    {
        "model": "socialaccount.socialtoken",
        "pk": 18,
        "fields": {
            "app": 1,
            "account": 18,
            "token": "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",
            "token_secret": "",
            "expires_at": null
        }
    },
    {
        "model": "socialaccount.socialtoken",
        "pk": 19,
        "fields": {
            "app": 1,
            "account": 19,
            "token": "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",
            "token_secret": "",
            "expires_at": null
        }
    },
    {
        "model": "socialaccount.socialtoken",
        "pk": 20,
        "fields": {
            "app": 1,
            "account": 20,
            "token": "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",
            "token_secret": "",
            "expires_at": null
        }
    },
    {
        "model": "socialaccount.socialtoken",
        "pk": 21,
        "fields": {
            "app": 1,
            "account": 21,
            "token": "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",
            "token_secret": "",
            "expires_at": null
        }
    },
    {
        "model": "socialaccount.socialtoken",
        "pk": 22,
        "fields": {
            "app": 1,
            "account": 22,
            "token": "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",
            "token_secret": "",
            "expires_at": null
        }
    },
    {
        "model": "socialaccount.socialtoken",
        "pk": 23,
        "fields": {
            "app": 1,
            "account": 23,
            "token": "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",
            "token_secret": "",
            "expires_at": null
        }
    },
    {
        "model": "socialaccount.socialtoken",
        "pk": 24,
        "fields": {
            "app": 1,
            "account": 24,
            "token": "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",
            "token_secret": "",
            "expires_at": null
        }
    },
    {
        "model": "socialaccount.socialtoken",
        "pk": 25,
        "fields": {
            "app": 1,
            "account": 25,
            "token": "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",
            "token_secret": "",
            "expires_at": null
        }
    },
    {
        "model": "socialaccount.socialtoken",
        "pk": 26,
        "fields": {
            "app": 1,
            "account": 26,
            "token": "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",
            "token_secret": "",
            "expires_at": null
        }
    },
    {
        "model": "socialaccount.socialtoken",
        "pk": 27,
        "fields": {
            "app": 1,
            "account": 27,
            "token": "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",
            "token_secret": "",
            "expires_at": null
        }
    },
    {
        "model": "socialaccount.socialtoken",
        "pk": 28,
        "fields": {
            "app": 1,
            "account": 28,
            "token": "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",
            "token_secret": "",
            "expires_at": null
        }
    },
    {
        "model": "socialaccount.socialtoken",
        "pk": 29,
        "fields": {
            "app": 1,
            "account": 29,
            "token": "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",
            "token_secret": "",
            "expires_at": null
        }
    },
    {
        "model": "socialaccount.socialtoken",
        "pk": 30,
        "fields": {
            "app": 1,
            "account": 30,
            "token": "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",
            "token_secret": "",
            "expires_at": null
        }
    },
    {
        "model": "socialaccount.socialtoken",
        "pk": 31,
        "fields": {
            "app": 1,
            "account": 31,
            "token": "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",
            "token_secret": "",
            "expires_at": null
        }
    },
    {
        "model": "socialaccount.socialtoken",
        "pk": 32,
        "fields": {
            "app": 1,
            "account": 32,
            "token": "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",
            "token_secret": "",
            "expires_at": null
        }
    },
    {
        "model": "socialaccount.socialtoken",
        "pk": 33,
        "fields": {
            "app": 1,
            "account": 33,
            "token": "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",
            "token_secret": "",
            "expires_at": null
        }
    },
    {
        "model": "socialaccount.socialtoken",
        "pk": 34,
        "fields": {
            "app": 1,
            "account": 34,
            "token": "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",
            "token_secret": "",
            "expires_at": null
        }
    },
    {
        "model": "socialaccount.socialtoken",
        "pk": 35,
        "fields": {
            "app": 1,
            "account": 35,
            "token": "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",
            "token_secret": "",
            "expires_at": null
        }
    },
    {
        "model": "socialaccount.socialtoken",
        "pk": 36,
        "fields": {
            "app": 1,
            "account": 36,
            "token": "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",
            "token_secret": "",
            "expires_at": null
        }
    },
    {
        "model": "socialaccount.socialtoken",
        "pk": 37,
        "fields": {
            "app": 1,
            "account": 37,
            "token": "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",
            "token_secret": "",
            "expires_at": null
        }
    },
    {
        "model": "socialaccount.socialtoken",
        "pk": 38,
        "fields": {
            "app": 1,
            "account": 38,
            "token": "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",
            "token_secret": "",
            "expires_at": null
        }
    },
    {
        "model": "socialaccount.socialtoken",
        "pk": 39,
        "fields": {
            "app": 1,
            "account": 39,
            "token": "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",
            "token_secret": "",
            "expires_at": null
        }
    }
]