[
    {
        "model": "authtoken.token",
        "pk": "031ea19e8f6a72d8131689dc5f76e3abdc0840be",
        "fields": {
            "user": 41,
            "created": "2022-01-06T15:06:24.884Z"
        }
    },
    {
        "model": "authtoken.token",
        "pk": "2211c6e2ef13a7fded9caf4d8d9ff61e23081428",
        "fields": {
            "user": 29,
            "created": "2022-01-06T15:06:04.625Z"
        }
    },
    {
        "model": "authtoken.token",
        "pk": "23c5318f8f82ea7ef753f8ce2559b707bec3996f",
        "fields": {
            "user": 30,
            "created": "2022-01-06T15:06:04.741Z"
        }
    },
    {
        "model": "authtoken.token",
        "pk": "282c99a2b817da6fef46f2a71a9262c5e9b5a880",
        "fields": {
            "user": 27,
            "created": "2022-01-06T15:06:19.766Z"
        }
    },
    {
        "model": "authtoken.token",
        "pk": "2ac68c794a1e9f5735faaca7fbbebe83cbb3deff",
        "fields": {
            "user": 32,
            "created": "2022-01-06T15:06:05.438Z"
        }
    },
    {
        "model": "authtoken.token",
        "pk": "3c3ad6ef17bd00353bdb7f82c8d91ac0a478589f",
        "fields": {
            "user": 43,
            "created": "2022-01-06T15:06:36.971Z"
        }
    },
    {
        "model": "authtoken.token",
        "pk": "4176a1a1985a1524500dd45f826ae04262a5c1f0",
        "fields": {
            "user": 14,
            "created": "2022-01-06T15:02:44.075Z"
        }
    },
    {
        "model": "authtoken.token",
        "pk": "4e547db0bfa0aa8a78b0466d057ce559ce32d28e",
        "fields": {
            "user": 45,
            "created": "2022-01-06T15:08:45.750Z"
        }
    },
    {
        "model": "authtoken.token",
        "pk": "53183a6362a36bd291291ee57f44e70c095c7a9b",
        "fields": {
            "user": 28,
            "created": "2022-01-06T15:06:01.927Z"
        }
    },
    {
        "model": "authtoken.token",
        "pk": "54adc47885123943179330401d3926ae2442c789",
        "fields": {
            "user": 26,
            "created": "2022-01-06T15:05:57.647Z"
        }
    },
    {
        "model": "authtoken.token",
        "pk": "700d6009176bae31a410b8f339b326419f33c28d",
        "fields": {
            "user": 25,
            "created": "2022-01-06T15:05:56.612Z"
        }
    },
    {
        "model": "authtoken.token",
        "pk": "772b715fa64c0584200bf57141b181cae3b822ba",
        "fields": {
            "user": 39,
            "created": "2022-01-06T15:06:22.828Z"
        }
    },
    {
        "model": "authtoken.token",
        "pk": "795a19fc521e12cda42bb57c9efcc3c156b9fbdf",
        "fields": {
            "user": 16,
            "created": "2022-01-06T15:05:48.817Z"
        }
    },
    {
        "model": "authtoken.token",
        "pk": "7a8c7a094b756cec9fb73eab78678e5bb714815c",
        "fields": {
            "user": 37,
            "created": "2022-01-06T15:06:12.781Z"
        }
    },
    {
        "model": "authtoken.token",
        "pk": "7bace79c3192428567e5e81746bfbc4c81a353a2",
        "fields": {
            "user": 18,
            "created": "2022-01-06T15:05:50.568Z"
        }
    },
    {
        "model": "authtoken.token",
        "pk": "86c4772ac132b9025468b8d4bcf829da9cbdbc7f",
        "fields": {
            "user": 36,
            "created": "2022-01-06T15:06:07.852Z"
        }
    },
    {
        "model": "authtoken.token",
        "pk": "8a94052c0b25f23098a62d989bacb89b5ba9ba77",
        "fields": {
            "user": 21,
            "created": "2022-01-06T15:05:53.500Z"
        }
    },
    {
        "model": "authtoken.token",
        "pk": "a070c746b9b08e8796135deb072997ce30705dc3",
        "fields": {
            "user": 24,
            "created": "2022-01-06T15:05:55.440Z"
        }
    },
    {
        "model": "authtoken.token",
        "pk": "aa452d4cfd7e4707e694880fb4104345d4353df0",
        "fields": {
            "user": 1,
            "created": "2020-12-21T02:33:33.030Z"
        }
    },
    {
        "model": "authtoken.token",
        "pk": "adf77d55f78a113b13b03650672410f21a56c3ea",
        "fields": {
            "user": 15,
            "created": "2022-01-06T15:02:57.730Z"
        }
    },
    {
        "model": "authtoken.token",
        "pk": "af9c9fc0daba6c49d380720b703fa671e76d783a",
        "fields": {
            "user": 34,
            "created": "2022-01-06T15:06:06.690Z"
        }
    },
    {
        "model": "authtoken.token",
        "pk": "b52447e4adc49fd0776a5e9486a221047c52c155",
        "fields": {
            "user": 31,
            "created": "2022-01-06T15:06:05.066Z"
        }
    },
    {
        "model": "authtoken.token",
        "pk": "b656f0c9b897565b640b59772a66fafbf0e6de38",
        "fields": {
            "user": 44,
            "created": "2022-01-06T15:06:49.863Z"
        }
    },
    {
        "model": "authtoken.token",
        "pk": "beb3f25fa5ae8608c15036743b2f10c439346b4f",
        "fields": {
            "user": 19,
            "created": "2022-01-06T15:05:51.168Z"
        }
    },
    {
        "model": "authtoken.token",
        "pk": "c0d2f1f9a2be1065cf2ef8a7637c100af859b256",
        "fields": {
            "user": 22,
            "created": "2022-01-06T15:05:54.436Z"
        }
    },
    {
        "model": "authtoken.token",
        "pk": "c855fb3b982d05c75d7d3eb306022256a9bacda5",
        "fields": {
            "user": 23,
            "created": "2022-01-06T15:05:54.930Z"
        }
    },
    {
        "model": "authtoken.token",
        "pk": "c85d27f32d6638a21dfec944058322425c2ebae9",
        "fields": {
            "user": 33,
            "created": "2022-01-06T15:06:05.970Z"
        }
    },
    {
        "model": "authtoken.token",
        "pk": "c88c7c25169a2131e735cd567e8e699d4fe2a1ec",
        "fields": {
            "user": 20,
            "created": "2022-01-06T15:05:52.912Z"
        }
    },
    {
        "model": "authtoken.token",
        "pk": "ce4f5c51fb662aea0dfb4920cf3241e85198cd50",
        "fields": {
            "user": 38,
            "created": "2022-01-06T15:06:18.220Z"
        }
    },
    {
        "model": "authtoken.token",
        "pk": "e0038006339fd550c31ba59dcf3e7ea778829382",
        "fields": {
            "user": 40,
            "created": "2022-01-06T15:06:22.868Z"
        }
    },
    {
        "model": "authtoken.token",
        "pk": "e10132fe1553ea2decc8e1a844f7b089534a5a8c",
        "fields": {
            "user": 17,
            "created": "2022-01-06T15:05:50.074Z"
        }
    },
    {
        "model": "authtoken.token",
        "pk": "eacaa8bf1a3cd3f39b51909bb7292f112dcce6db",
        "fields": {
            "user": 35,
            "created": "2022-01-06T15:06:07.597Z"
        }
    },
    {
        "model": "authtoken.token",
        "pk": "efb2106ebe9168e40deb1711d90c7d31e052045d",
        "fields": {
            "user": 42,
            "created": "2022-01-06T15:06:26.289Z"
        }
    }
]